cbm_explorer/__init__.py
cbm_explorer/continent.py
cbm_explorer/country.py
cbm_explorer/volinc_db.py
cbm_explorer-0.1.1.dist-info/LICENSE.txt
cbm_explorer-0.1.1.dist-info/METADATA
cbm_explorer-0.1.1.dist-info/WHEEL
cbm_explorer-0.1.1.dist-info/top_level.txt
cbm_explorer-0.1.1.dist-info/RECORD
