Metadata-Version: 2.1
Name: cbm-explorer
Version: 0.1.1
Summary: A package for exploring the results of a CBM run and the corresponding Access databases.
Home-page: UNKNOWN
Author: Lucas Sinclair
Author-email: lucas.sinclair@me.com
License: MIT
Platform: UNKNOWN
Requires-Dist: autopaths
Requires-Dist: plumbing
Requires-Dist: pandas
